{
  "schemaVersion": 1,
  "source": "local-auth-server.mjs#RPC_PERMISSIONS",
  "expectedCount": 48,
  "permissions": {
    "administer_nursing_medication_secure": { "module": "enfermagem", "action": "can_edit" },
    "bedside_check": { "module": "enfermagem", "action": "can_view" },
    "calc_imc": { "module": "prontuario", "action": "can_view" },
    "call_nursing_triage_secure": { "module": "enfermagem", "action": "can_edit" },
    "cancel_schedule_block_secure": { "module": "agenda", "action": "can_edit" },
    "close_waitlist_entry_secure": { "module": "agenda", "action": "can_edit" },
    "complete_nursing_triage_secure": { "module": "enfermagem", "action": "can_edit" },
    "convert_waitlist_to_appointment_secure": { "module": "agenda", "action": "can_edit" },
    "create_appointment_secure": { "module": "agenda", "action": "can_create" },
    "create_appointment_with_requirements_secure": { "module": "agenda", "action": "can_create" },
    "create_billing_secure": { "module": "faturamento", "action": "can_create" },
    "create_medical_record_secure": { "module": "prontuario", "action": "can_create" },
    "create_nursing_medication_secure": { "module": "enfermagem", "action": "can_edit" },
    "create_nursing_shift_handoff_secure": { "module": "enfermagem", "action": "can_create" },
    "create_professional_payment": { "module": "financeiro", "action": "can_create" },
    "create_schedule_block_secure": { "module": "agenda", "action": "can_edit" },
    "create_waitlist_entry_secure": { "module": "agenda", "action": "can_create" },
    "current_company_id": { "module": "admin", "action": "can_view" },
    "enqueue_nursing_triage_secure": { "module": "enfermagem", "action": "can_create" },
    "finalize_medical_attendance_secure": { "module": "prontuario", "action": "can_create" },
    "get_billing_balance_secure": { "module": "financeiro", "action": "can_view" },
    "get_professional_available_slots": { "module": "agenda", "action": "can_view" },
    "get_reception_checkin_readiness": { "module": "recepcao", "action": "can_view" },
    "get_scheduling_requirements": { "module": "agenda", "action": "can_view" },
    "list_billing_financial_summary_secure": { "module": "financeiro", "action": "can_view" },
    "list_billing_production_secure": { "module": "faturamento", "action": "can_view" },
    "list_professional_payments": { "module": "financeiro", "action": "can_view" },
    "list_tiss_glosas_read_secure": { "module": "faturamento", "action": "can_view" },
    "list_tiss_protocols_read_secure": { "module": "faturamento", "action": "can_view" },
    "list_tiss_read_model_secure": { "module": "faturamento", "action": "can_view" },
    "mark_overdue_appointments_no_show_secure": { "module": "agenda", "action": "can_edit" },
    "perform_reception_checkin_secure": { "module": "recepcao", "action": "can_create" },
    "record_billing_receipt_secure": { "module": "financeiro", "action": "can_create" },
    "record_confirmation_attempt_secure": { "module": "agenda", "action": "can_edit" },
    "record_nursing_procedure_secure": { "module": "enfermagem", "action": "can_create" },
    "refresh_confirmation_queue_secure": { "module": "agenda", "action": "can_edit" },
    "refuse_nursing_medication_secure": { "module": "enfermagem", "action": "can_edit" },
    "report_nursing_incident_secure": { "module": "enfermagem", "action": "can_create" },
    "reschedule_appointment_secure": { "module": "agenda", "action": "can_edit" },
    "reverse_billing_receipt_secure": { "module": "financeiro", "action": "can_edit" },
    "save_or_release_lab_result_secure": { "module": "laboratorio", "action": "can_edit" },
    "sign_medical_record_secure": { "module": "prontuario", "action": "can_edit" },
    "transition_professional_payment": { "module": "financeiro", "action": "can_edit" },
    "update_appointment_status_secure": { "module": "agenda", "action": "can_edit" },
    "update_billing_status_secure": { "module": "faturamento", "action": "can_edit" },
    "update_medical_record_secure": { "module": "prontuario", "action": "can_edit" },
    "update_reception_authorization_secure": { "module": "recepcao", "action": "can_edit" },
    "update_reception_eligibility_secure": { "module": "recepcao", "action": "can_edit" }
  },
  "signatures": {
    "administer_nursing_medication_secure": "p_admin_id bigint, p_patient_confirmed_id bigint, p_idempotency_key uuid",
    "bedside_check": "p_admin_id bigint, p_patient_confirmado bigint",
    "calc_imc": "p_peso numeric, p_altura_cm numeric",
    "call_nursing_triage_secure": "p_queue_id bigint, p_idempotency_key uuid",
    "cancel_schedule_block_secure": "p_block_id bigint",
    "close_waitlist_entry_secure": "p_waitlist_id bigint, p_status text, p_reason text",
    "complete_nursing_triage_secure": "p_queue_id bigint, p_appointment_id bigint, p_classification_id integer, p_triage jsonb, p_idempotency_key uuid",
    "convert_waitlist_to_appointment_secure": "p_waitlist_id bigint, p_appointment_date date, p_start_time time without time zone, p_end_time time without time zone",
    "create_appointment_secure": "p_patient_id bigint, p_professional_id bigint, p_appointment_date date, p_start_time time without time zone, p_end_time time without time zone, p_company_id uuid, p_unit_id integer, p_specialty_id integer, p_service_id bigint, p_appointment_type_id bigint, p_status text, p_is_return boolean, p_is_walkin boolean, p_notes text",
    "create_appointment_with_requirements_secure": "p_patient_id bigint, p_professional_id bigint, p_appointment_date date, p_start_time time without time zone, p_end_time time without time zone, p_company_id uuid, p_unit_id integer, p_specialty_id integer, p_service_id bigint, p_appointment_type_id bigint, p_status text, p_is_return boolean, p_is_walkin boolean, p_notes text, p_insurance_id integer, p_card_number text, p_authorization_number text",
    "create_billing_secure": "p_appointment_id bigint, p_amount numeric, p_tiss_status text, p_guide_number text",
    "create_medical_record_secure": "p_patient_id bigint, p_professional_id bigint, p_appointment_id bigint, p_record_date date, p_anamnesis text, p_evolution text, p_diagnosis text, p_prescription text, p_vital_signs jsonb, p_notes text",
    "create_nursing_medication_secure": "p_patient_id bigint, p_medication text, p_dose text, p_via text, p_scheduled_at timestamp with time zone, p_idempotency_key uuid",
    "create_nursing_shift_handoff_secure": "p_shift_date date, p_shift_type text, p_summary text, p_pending_items jsonb, p_critical_patients jsonb, p_notes text, p_idempotency_key uuid",
    "create_professional_payment": "p_idempotency_key uuid, p_professional_id bigint, p_unit_id bigint, p_reference_date date, p_reference_description text, p_total_procedures integer, p_total_value numeric, p_total_received numeric, p_remuneration_type text, p_percentage numeric, p_observation text",
    "create_schedule_block_secure": "p_starts_at timestamp with time zone, p_ends_at timestamp with time zone, p_reason text, p_professional_id bigint, p_unit_id integer, p_block_type text",
    "create_waitlist_entry_secure": "p_patient_id bigint, p_reason text, p_professional_id bigint, p_specialty_id integer, p_appointment_type_id bigint, p_unit_id integer, p_preferred_date_from date, p_preferred_date_to date, p_preferred_period text, p_priority text, p_notes text",
    "current_company_id": "",
    "enqueue_nursing_triage_secure": "p_patient_id bigint, p_initial_complaint text, p_classification_id integer, p_idempotency_key uuid",
    "finalize_medical_attendance_secure": "p_appointment_id bigint, p_record_date date, p_anamnesis text, p_evolution text, p_diagnosis text, p_prescription text, p_vital_signs jsonb, p_notes text",
    "get_billing_balance_secure": "p_billing_id bigint",
    "get_professional_available_slots": "p_professional_id bigint, p_date date, p_duration_minutes integer, p_unit_id integer",
    "get_reception_checkin_readiness": "p_appointment_id bigint",
    "get_scheduling_requirements": "p_patient_id bigint, p_professional_id bigint, p_service_id bigint, p_insurance_id integer, p_card_number text",
    "list_billing_financial_summary_secure": "",
    "list_billing_production_secure": "",
    "list_professional_payments": "p_professional_id bigint, p_unit_id bigint, p_status text, p_reference_from date, p_reference_to date, p_limit integer, p_offset integer, p_search text",
    "list_tiss_glosas_read_secure": "p_tiss_xml_id bigint",
    "list_tiss_protocols_read_secure": "",
    "list_tiss_read_model_secure": "p_year integer, p_month integer, p_insurance_company_id integer",
    "mark_overdue_appointments_no_show_secure": "p_date date, p_grace_minutes integer",
    "perform_reception_checkin_secure": "p_appointment_id bigint, p_priority text, p_exception_reason text",
    "record_billing_receipt_secure": "p_billing_id bigint, p_amount numeric, p_payment_method text, p_idempotency_key uuid",
    "record_confirmation_attempt_secure": "p_queue_id bigint, p_channel text, p_outcome text, p_notes text",
    "record_nursing_procedure_secure": "p_patient_id bigint, p_procedure_type text, p_description text, p_faturavel boolean, p_idempotency_key uuid",
    "refresh_confirmation_queue_secure": "p_days_ahead integer",
    "refuse_nursing_medication_secure": "p_admin_id bigint, p_reason text, p_idempotency_key uuid",
    "report_nursing_incident_secure": "p_patient_id bigint, p_incident_type text, p_severity text, p_description text, p_idempotency_key uuid",
    "reschedule_appointment_secure": "p_appointment_id bigint, p_new_appointment_date date, p_new_start_time time without time zone, p_new_end_time time without time zone, p_reason text",
    "reverse_billing_receipt_secure": "p_receipt_id bigint, p_reason text, p_idempotency_key uuid",
    "save_or_release_lab_result_secure": "p_item_id bigint, p_expected_status text, p_idempotency_key uuid, p_results jsonb, p_release boolean",
    "sign_medical_record_secure": "p_record_id bigint",
    "transition_professional_payment": "p_idempotency_key uuid, p_payment_id bigint, p_target_status text, p_reason text, p_payment_date date",
    "update_appointment_status_secure": "p_appointment_id bigint, p_new_status text, p_reason text",
    "update_billing_status_secure": "p_billing_id bigint, p_status text, p_reason text",
    "update_medical_record_secure": "p_record_id bigint, p_patch jsonb",
    "update_reception_authorization_secure": "p_authorization_id uuid, p_status text, p_protocol_number text, p_authorization_number text, p_password_number text, p_valid_until date, p_quantity_authorized integer, p_reason text",
    "update_reception_eligibility_secure": "p_eligibility_id uuid, p_status text, p_protocol_number text, p_result_detail text"
  },
  "functions": [
    "administer_nursing_medication_secure",
    "bedside_check",
    "calc_imc",
    "call_nursing_triage_secure",
    "cancel_schedule_block_secure",
    "close_waitlist_entry_secure",
    "complete_nursing_triage_secure",
    "convert_waitlist_to_appointment_secure",
    "create_appointment_secure",
    "create_appointment_with_requirements_secure",
    "create_billing_secure",
    "create_medical_record_secure",
    "create_nursing_medication_secure",
    "create_nursing_shift_handoff_secure",
    "create_professional_payment",
    "create_schedule_block_secure",
    "create_waitlist_entry_secure",
    "current_company_id",
    "enqueue_nursing_triage_secure",
    "finalize_medical_attendance_secure",
    "get_billing_balance_secure",
    "get_professional_available_slots",
    "get_reception_checkin_readiness",
    "get_scheduling_requirements",
    "list_billing_financial_summary_secure",
    "list_billing_production_secure",
    "list_professional_payments",
    "list_tiss_glosas_read_secure",
    "list_tiss_protocols_read_secure",
    "list_tiss_read_model_secure",
    "mark_overdue_appointments_no_show_secure",
    "perform_reception_checkin_secure",
    "record_billing_receipt_secure",
    "record_confirmation_attempt_secure",
    "record_nursing_procedure_secure",
    "refresh_confirmation_queue_secure",
    "refuse_nursing_medication_secure",
    "report_nursing_incident_secure",
    "reschedule_appointment_secure",
    "reverse_billing_receipt_secure",
    "save_or_release_lab_result_secure",
    "sign_medical_record_secure",
    "transition_professional_payment",
    "update_appointment_status_secure",
    "update_billing_status_secure",
    "update_medical_record_secure",
    "update_reception_authorization_secure",
    "update_reception_eligibility_secure"
  ]
}

